svphaser/__init__.py
svphaser/__main__.py
svphaser/_version.py
svphaser/cli.py
svphaser/logging.py
svphaser/py.typed
svphaser/phasing/__init__.py
svphaser/phasing/_workers.py
svphaser/phasing/algorithms.py
svphaser/phasing/io.py
svphaser/phasing/types.py
svphaser-2.1.0.dist-info/METADATA
svphaser-2.1.0.dist-info/WHEEL
svphaser-2.1.0.dist-info/entry_points.txt
svphaser-2.1.0.dist-info/licenses/LICENSE
svphaser-2.1.0.dist-info/RECORD
