Metadata-Version: 2.4
Name: svphaser
Version: 2.1.0
Summary: Structural-variant phasing from HP-tagged long-read BAMs
Project-URL: Homepage, https://github.com/SFGLab/SvPhaser
Project-URL: Issues, https://github.com/SFGLab/SvPhaser/issues
Project-URL: Source, https://github.com/SFGLab/SvPhaser
Author-email: SvPhaser Team <you@lab.org>
License: MIT
License-File: LICENSE
Keywords: BAM,ONT,VCF,genomics,long-reads,phasing,structural-variants
Classifier: Development Status :: 4 - Beta
Classifier: Intended Audience :: Science/Research
Classifier: License :: OSI Approved :: MIT License
Classifier: Operating System :: OS Independent
Classifier: Programming Language :: Python
Classifier: Programming Language :: Python :: 3
Classifier: Programming Language :: Python :: 3.9
Classifier: Programming Language :: Python :: 3.10
Classifier: Programming Language :: Python :: 3.11
Classifier: Programming Language :: Python :: 3.12
Classifier: Topic :: Scientific/Engineering :: Bio-Informatics
Requires-Python: >=3.9
Requires-Dist: cyvcf2>=0.30
Requires-Dist: pandas>=2.1
Requires-Dist: pysam>=0.23
Requires-Dist: typer>=0.14
Provides-Extra: bench
Requires-Dist: py-spy>=0.3; extra == 'bench'
Requires-Dist: pytest-benchmark>=4.0; extra == 'bench'
Provides-Extra: dev
Requires-Dist: black>=24.3; extra == 'dev'
Requires-Dist: build>=1.2; extra == 'dev'
Requires-Dist: hypothesis>=6.90; extra == 'dev'
Requires-Dist: mypy>=1.8; extra == 'dev'
Requires-Dist: pandas-stubs>=2.0; extra == 'dev'
Requires-Dist: pre-commit>=3.6; extra == 'dev'
Requires-Dist: pytest-cov>=5; extra == 'dev'
Requires-Dist: pytest-xdist>=3.5; extra == 'dev'
Requires-Dist: pytest>=8; extra == 'dev'
Requires-Dist: ruff>=0.5; extra == 'dev'
Requires-Dist: tox>=4.10; extra == 'dev'
Requires-Dist: twine>=5.0; extra == 'dev'
Provides-Extra: plots
Requires-Dist: matplotlib>=3.7; extra == 'plots'
